{
    "<s>": 0,
    "</s>": 1,
    "t": 2,
    "ɪ": 3,
    "n": 4,
    "ɹ": 5,
    "s": 6,
    "d": 7,
    "l": 8,
    "k": 9,
    "ə": 10,
    "æ": 11,
    "ʌ": 12,
    "ð": 13,
    "ɛ": 14,
    "m": 15,
    "uː": 16,
    "w": 17,
    "z": 18,
    "iː": 19,
    "j": 20,
    "aɪ": 21,
    "oʊ": 22,
    "h": 23,
    "b": 24,
    "p": 25,
    "eɪ": 26,
    "ɡ": 27,
    "ɑː": 28,
    "i": 29,
    "ʊ": 30,
    "f": 31,
    "ɐ": 32,
    "ŋ": 33,
    "ɚ": 34,
    "v": 35,
    "ɔː": 36,
    "aʊ": 37,
    "ɾ": 38,
    "ɔ": 39,
    "ʃ": 40,
    "θ": 41,
    "ɜː": 42,
    "t̠ʃ": 43,
    "d̠ʒ": 44,
    "oː": 45,
    "ɔɪ": 46,
    "n̩": 47,
    "ʔ": 48,
    "ʒ": 49,
    "r": 50,
    "x": 51,
    "ɑ̃": 52,
    "nʲ": 53,
    "ɐɐ": 54,
    "iːː": 55
}